uuv_webrtc/__init__.py
uuv_webrtc/cv_cap_stream_track.py
uuv_webrtc/cv_capture.py
uuv_webrtc/rtc_client.py
uuv_webrtc/rtc_server.py
uuv_webrtc/sdp_server.py
uuv_webrtc/utils.py
uuv_webrtc/video_stream_receiver.py
uuv_webrtc-1.0.2.dist-info/METADATA
uuv_webrtc-1.0.2.dist-info/WHEEL
uuv_webrtc-1.0.2.dist-info/top_level.txt
uuv_webrtc-1.0.2.dist-info/RECORD
