Metadata-Version: 2.4
Name: uuv_webrtc
Version: 1.0.2
Summary: UUV WebRTC Video Transmission System
Author-email: FEITENG <wxfeit@163.com>
License: MIT
Project-URL: Homepage, https://github.com/FEITENG-0828/uuv_webrtc
Classifier: Programming Language :: Python :: 3
Classifier: License :: OSI Approved :: MIT License
Classifier: Operating System :: OS Independent
Requires-Python: >=3.9
Requires-Dist: aioice==0.9.0
Requires-Dist: aiortc==1.10.1
Requires-Dist: av==13.1.0
Requires-Dist: cffi==1.17.1
Requires-Dist: cryptography==44.0.1
Requires-Dist: dnspython==2.7.0
Requires-Dist: google-crc32c==1.6.0
Requires-Dist: ifaddr==0.2.0
Requires-Dist: numpy==2.2.3
Requires-Dist: opencv-python==4.11.0.86
Requires-Dist: pycparser==2.22
Requires-Dist: pyee==12.1.1
Requires-Dist: pylibsrtp==0.11.0
Requires-Dist: pyOpenSSL==25.0.0
Requires-Dist: typing_extensions==4.12.2
